wisteria/__init__.py
wisteria/aboutproject.py
wisteria/cfgfile.py
wisteria/classesexamples/simpleclasses.py
wisteria/cmdline_cmp.py
wisteria/cmdline_mymachine.py
wisteria/cmdline_output.py
wisteria/cwc/cwc_utils.py
wisteria/cwc/pgnreader/cwc_default.py
wisteria/cwc/pgnreader/cwc_iaswn.py
wisteria/cwc/pgnreader/works_as_expected.py
wisteria/cwc/simple/cwc_default.py
wisteria/cwc/simple/cwc_iaswn.py
wisteria/cwc/simple/works_as_expected.py
wisteria/data.py
wisteria/dmfile.py
wisteria/filterstr.py
wisteria/globs.py
wisteria/helpmsg.py
wisteria/matplotgraphs.py
wisteria/msg.py
wisteria/report.py
wisteria/reprfmt.py
wisteria/results.py
wisteria/serializers.py
wisteria/serializers_classes.py
wisteria/textandnotes.py
wisteria/utils.py
wisteria/wisteria.py
wisteria/wisteriaerror.py
wisteria-0.2.3.dist-info/entry_points.txt
wisteria-0.2.3.dist-info/LICENSE
wisteria-0.2.3.dist-info/WHEEL
wisteria-0.2.3.dist-info/METADATA
wisteria-0.2.3.dist-info/RECORD
