Metadata-Version: 2.1
Name: wisteria
Version: 0.2.3
Summary: Python serializers comparisons
License: GPLv3
Author: suizokukan
Author-email: suizokukan@orange.fr
Requires-Python: >=3.8,<4.0
Classifier: License :: Other/Proprietary License
Classifier: Programming Language :: Python :: 3
Classifier: Programming Language :: Python :: 3.10
Classifier: Programming Language :: Python :: 3.8
Classifier: Programming Language :: Python :: 3.9
Requires-Dist: psutil (>=5.8.0,<6.0.0)
Requires-Dist: py-cpuinfo (>=8.0.0,<9.0.0)
Requires-Dist: rich (>=10.11.0,<11.0.0)
Requires-Dist: wmi (==1.5.1); sys_platform == "win32"
